LICENSE
README.md
browsable_router/__init__.py
browsable_router/meta.py
browsable_router/permissions.py
browsable_router/router.py
browsable_router/typing.py
browsable_router/views.py
django_browsable_router-0.2.4.dist-info/LICENSE
django_browsable_router-0.2.4.dist-info/WHEEL
django_browsable_router-0.2.4.dist-info/METADATA
django_browsable_router-0.2.4.dist-info/RECORD
