Metadata-Version: 2.1
Name: django-browsable-router
Version: 0.2.4
Summary: A Django REST Framework router that can show APIViews and include other routers as navigable urls in the root view.
Home-page: https://github.com/MrThearMan/django-browsable-router
License: MIT
Keywords: django,djangorestframework,drf
Author: Matti Lamppu
Author-email: lamppu.matti.akseli@gmail.com
Requires-Python: >=3.7,<4
Classifier: Environment :: Web Environment
Classifier: Framework :: Django
Classifier: Framework :: Django :: 1.10
Classifier: Framework :: Django :: 1.11
Classifier: Framework :: Django :: 2.0
Classifier: Framework :: Django :: 2.1
Classifier: Framework :: Django :: 2.2
Classifier: Framework :: Django :: 3.0
Classifier: Framework :: Django :: 3.1
Classifier: Framework :: Django :: 3.2
Classifier: Framework :: Django :: 4.0
Classifier: Intended Audience :: Developers
Classifier: License :: OSI Approved :: MIT License
Classifier: Natural Language :: English
Classifier: Operating System :: OS Independent
Classifier: Programming Language :: Python
Classifier: Programming Language :: Python :: 3
Classifier: Programming Language :: Python :: 3 :: Only
Classifier: Programming Language :: Python :: 3.10
Classifier: Programming Language :: Python :: 3.7
Classifier: Programming Language :: Python :: 3.8
Classifier: Programming Language :: Python :: 3.9
Provides-Extra: typing
Requires-Dist: Django (>=1.10)
Requires-Dist: djangorestframework (>=3.7.0)
Requires-Dist: typing-extensions (>=4.0); extra == "typing"
Project-URL: Bug Tracker, https://github.com/MrThearMan/django-browsable-router/issues
Project-URL: Repository, https://github.com/MrThearMan/django-browsable-router
